symfit/__init__.py
symfit/api.py
symfit/distributions.py
symfit/contrib/__init__.py
symfit/contrib/interactive_guess/__init__.py
symfit/contrib/interactive_guess/interactive_guess.py
symfit/contrib/interactive_guess/examples/ODE_2D_example.py
symfit/contrib/interactive_guess/examples/ODE_example.py
symfit/contrib/interactive_guess/examples/simple_2D_example.py
symfit/contrib/interactive_guess/examples/simple_3D_example.py
symfit/contrib/interactive_guess/examples/vector_valued_2D.py
symfit/contrib/interactive_guess/tests/test_interactive_fit.py
symfit/core/__init__.py
symfit/core/argument.py
symfit/core/fit.py
symfit/core/fit_results.py
symfit/core/minimizers.py
symfit/core/models.py
symfit/core/objectives.py
symfit/core/operators.py
symfit/core/printing.py
symfit/core/support.py
symfit-0.5.6.dist-info/AUTHORS.rst
symfit-0.5.6.dist-info/LICENSE
symfit-0.5.6.dist-info/METADATA
symfit-0.5.6.dist-info/WHEEL
symfit-0.5.6.dist-info/pbr.json
symfit-0.5.6.dist-info/top_level.txt
symfit-0.5.6.dist-info/RECORD
