Metadata-Version: 2.1
Name: symfit
Version: 0.5.6
Summary: Symbolic Fitting; fitting as it should be.
Home-page: https://github.com/tBuLi/symfit
Author: Martin Roelfs
Author-email: martin.roelfs@kuleuven.be
License: MIT
Keywords: fit fitting symbolic
Classifier: Development Status :: 4 - Beta
Classifier: Intended Audience :: Science/Research
Classifier: Topic :: Scientific/Engineering
Classifier: License :: OSI Approved :: MIT License
Classifier: Programming Language :: Python :: 3
Classifier: Programming Language :: Python :: 3.7
Classifier: Programming Language :: Python :: 3.8
Classifier: Programming Language :: Python :: 3.9
Classifier: Programming Language :: Python :: 3.10
Classifier: Programming Language :: Python :: 3.11
Provides-Extra: contrib
Provides-Extra: all
License-File: LICENSE
License-File: AUTHORS.rst
